data_generator/__init__.py
data_generator/__main__.py
data_generator/cli_parser.py
data_generator/generator.py
data_generator/main.py
data_generator/output.py
data_generator/toml.py
Data_Generator-1.0.1.dist-info/METADATA
Data_Generator-1.0.1.dist-info/WHEEL
Data_Generator-1.0.1.dist-info/top_level.txt
Data_Generator-1.0.1.dist-info/RECORD
