Metadata-Version: 2.1
Name: Data-Generator
Version: 1.0.1
Summary: Random Data Generator
Home-page: https://github.com/bednaJedna/data_generator
Author: bednaJedna
Author-email: bednarik.radek@gmail.com
License: UNKNOWN
Keywords: random data generator python3
Platform: UNKNOWN
Classifier: License :: OSI Approved :: MIT License
Classifier: Programming Language :: Python :: 3
Classifier: Operating System :: OS Independent
Requires-Python: >=3.8
Requires-Dist: tqdm
Requires-Dist: XlsxWriter
Requires-Dist: tomlkit
Requires-Dist: pytest
